{
  "project_info": {
    "project_number": "1057669307066",
    "firebase_url": "https://myapplication-a306a.firebaseio.com",
    "project_id": "myapplication-a306a",
    "storage_bucket": "myapplication-a306a.appspot.com"
  },
  "client": [
    {
      "client_info": {
        "mobilesdk_app_id": "1:1057669307066:android:13c3c6a65bcbec53",
        "android_client_info": {
          "package_name": "com.example.myapplication"
        }
      },
      "oauth_client": [
        {
          "client_id": "1057669307066-7jp3hs3neoj1rj88lb7m36ghp6pv0sgh.apps.googleusercontent.com",
          "client_type": 1,
          "android_info": {
            "package_name": "com.example.myapplication",
            "certificate_hash": "201a0ae950a21492a85b2b068e46058c456b2e16"
          }
        },
        {
          "client_id": "1057669307066-t9jucnthss2k7ahrmfppien96phqldae.apps.googleusercontent.com",
          "client_type": 3
        }
      ],
      "api_key": [
        {
          "current_key": "AIzaSyCM3vtGtEZHnZGEFzQtG95MUYRaCJa9w8Y"
        }
      ],
      "services": {
        "appinvite_service": {
          "other_platform_oauth_client": [
            {
              "client_id": "1057669307066-t9jucnthss2k7ahrmfppien96phqldae.apps.googleusercontent.com",
              "client_type": 3
            }
          ]
        }
      }
    }
  ],
  "configuration_version": "1"
}